sa/__init__.py
sa/annotated/__init__.py
sa/annotated/numpy/__init__.py
sa/annotated/numpy/annotated.py
sa/annotated/pandas/__init__.py
sa/annotated/pandas/annotated.py
sa/annotated/pandas/series.py
sa/annotation/__init__.py
sa/annotation/annotation.py
sa/annotation/config.py
sa/annotation/dag.py
sa/annotation/sa.py
sa/annotation/unevaluated.py
sa/annotation/split_types/__init__.py
sa/annotation/split_types/generics.py
sa/annotation/split_types/split_types.py
sa/annotation/vm/__init__.py
sa/annotation/vm/driver.py
sa/annotation/vm/instruction.py
sa/annotation/vm/program.py
sa/annotation/vm/vm.py
sa-0.0.4.dist-info/LICENSE
sa-0.0.4.dist-info/METADATA
sa-0.0.4.dist-info/WHEEL
sa-0.0.4.dist-info/top_level.txt
sa-0.0.4.dist-info/RECORD
