Metadata-Version: 2.1
Name: sa
Version: 0.0.4
Summary: Python split annotations package
Home-page: https://www.github.com/weld-project/split-annotations
Author: Shoumik Palkar
Author-email: shoumik@cs.stanford.edu
License: UNKNOWN
Platform: UNKNOWN
Classifier: Programming Language :: Python :: 3
Classifier: License :: OSI Approved :: BSD License
Classifier: Operating System :: OS Independent
Requires-Python: >=3.6
